emmett_sentry/__init__.py
emmett_sentry/__version__.py
emmett_sentry/_imports.py
emmett_sentry/ext.py
emmett_sentry/helpers.py
emmett_sentry/instrument.py
emmett_sentry-0.8.2.dist-info/METADATA
emmett_sentry-0.8.2.dist-info/WHEEL
emmett_sentry-0.8.2.dist-info/licenses/LICENSE
emmett_sentry-0.8.2.dist-info/RECORD
